hausnet/__init__.py
hausnet/builders.py
hausnet/coders.py
hausnet/config.py
hausnet/devices.py
hausnet/flow.py
hausnet/hausnet.py
hausnet/interactive_net.py
hausnet/plant.py
hausnet/states.py
hausnet/operators/__init__.py
hausnet/operators/operators.py
hausnet/operators/tap.py
test/__init__.py
test/helpers.py
test/test_api.py
test/test_builders.py
test/test_coders.py
test/test_devices.py
test/test_flow.py
test/test_plant.py
hausnet_server-0.0.8.dist-info/LICENSE
hausnet_server-0.0.8.dist-info/METADATA
hausnet_server-0.0.8.dist-info/WHEEL
hausnet_server-0.0.8.dist-info/top_level.txt
hausnet_server-0.0.8.dist-info/RECORD
