Metadata-Version: 2.1
Name: hausnet-server
Version: 0.0.8
Summary: A server for the HausNet protocol
Home-page: https://github.com/HausNet/hausnet-server
Author: Louis Calitz
Author-email: louis@hausnet.io
License: UNKNOWN
Platform: UNKNOWN
Classifier: Programming Language :: Python :: 3
Classifier: License :: OSI Approved :: MIT License
Classifier: Operating System :: OS Independent
Requires-Python: >=3.8
Requires-Dist: aioreactive (==0.5.0)
Requires-Dist: janus (==0.6.1)
Requires-Dist: packaging (==20.7)
Requires-Dist: paho-mqtt (==1.5.1)
Requires-Dist: phx-class-registry (==3.0.5)
Requires-Dist: pyparsing (==2.4.7)
